sequential_rename/__init__.py
sequential_rename/sequential_rename.py
sequential_rename-1.0.4.dist-info/licenses/LICENSE
sequential_rename-1.0.4.dist-info/METADATA
sequential_rename-1.0.4.dist-info/WHEEL
sequential_rename-1.0.4.dist-info/top_level.txt
sequential_rename-1.0.4.dist-info/RECORD
