Metadata-Version: 2.4
Name: sequential_rename
Version: 1.0.4
Summary: A small package for sequentially renaming files with the same name.
Author-email: "Stefan Mladenovic (Gizmotechy)" <stefan.mladenovic@live.com>
License-Expression: GPL-3.0-or-later
Project-URL: Homepage, https://github.com/GizmoTechy/Sequential-Rename
Project-URL: Issues, https://github.com/GizmoTechy/Sequential-Rename/issues
Classifier: Programming Language :: Python :: 3
Classifier: Operating System :: OS Independent
Requires-Python: >=3.10
License-File: LICENSE
Requires-Dist: paramiko
Requires-Dist: pysftp
Dynamic: license-file
